JscorpTechPayme
config
